{
  "meta": {
    "name": "spritesheet",
    "image": "/static/spritesheet.png",
    "format": "RGBA8888",
    "size": {
      "w": 1920,
      "h": 640
    },
    "scale": 1
  },
  "frames": {
    "white-king": {
      "frame": {
        "x": 0,
        "y": 0,
        "w": 320,
        "h": 320
      },
      "rotated": false,
      "trimmed": false,
      "spriteSourceSize": {
        "x": 0,
        "y": 0,
        "w": 320,
        "h": 320
      },
      "sourceSize": {
        "w": 320,
        "h": 320
      }
    },
    "white-queen": {
      "frame": {
        "x": 320,
        "y": 0,
        "w": 320,
        "h": 320
      },
      "rotated": false,
      "trimmed": false,
      "spriteSourceSize": {
        "x": 0,
        "y": 0,
        "w": 320,
        "h": 320
      },
      "sourceSize": {
        "w": 320,
        "h": 320
      }
    },
    "white-bishop": {
      "frame": {
        "x": 640,
        "y": 0,
        "w": 320,
        "h": 320
      },
      "rotated": false,
      "trimmed": false,
      "spriteSourceSize": {
        "x": 0,
        "y": 0,
        "w": 320,
        "h": 320
      },
      "sourceSize": {
        "w": 320,
        "h": 320
      }
    },
    "white-knight": {
      "frame": {
        "x": 960,
        "y": 0,
        "w": 320,
        "h": 320
      },
      "rotated": false,
      "trimmed": false,
      "spriteSourceSize": {
        "x": 0,
        "y": 0,
        "w": 320,
        "h": 320
      },
      "sourceSize": {
        "w": 320,
        "h": 320
      }
    },
    "white-rook": {
      "frame": {
        "x": 1280,
        "y": 0,
        "w": 320,
        "h": 320
      },
      "rotated": false,
      "trimmed": false,
      "spriteSourceSize": {
        "x": 0,
        "y": 0,
        "w": 320,
        "h": 320
      },
      "sourceSize": {
        "w": 320,
        "h": 320
      }
    },
    "white-pawn": {
      "frame": {
        "x": 1600,
        "y": 0,
        "w": 320,
        "h": 320
      },
      "rotated": false,
      "trimmed": false,
      "spriteSourceSize": {
        "x": 0,
        "y": 0,
        "w": 320,
        "h": 320
      },
      "sourceSize": {
        "w": 320,
        "h": 320
      }
    },
    "black-king": {
      "frame": {
        "x": 0,
        "y": 320,
        "w": 320,
        "h": 320
      },
      "rotated": false,
      "trimmed": false,
      "spriteSourceSize": {
        "x": 0,
        "y": 0,
        "w": 320,
        "h": 320
      },
      "sourceSize": {
        "w": 320,
        "h": 320
      }
    },
    "black-queen": {
      "frame": {
        "x": 320,
        "y": 320,
        "w": 320,
        "h": 320
      },
      "rotated": false,
      "trimmed": false,
      "spriteSourceSize": {
        "x": 0,
        "y": 0,
        "w": 320,
        "h": 320
      },
      "sourceSize": {
        "w": 320,
        "h": 320
      }
    },
    "black-bishop": {
      "frame": {
        "x": 640,
        "y": 320,
        "w": 320,
        "h": 320
      },
      "rotated": false,
      "trimmed": false,
      "spriteSourceSize": {
        "x": 0,
        "y": 320,
        "w": 320,
        "h": 320
      },
      "sourceSize": {
        "w": 320,
        "h": 320
      }
    },
    "black-knight": {
      "frame": {
        "x": 960,
        "y": 320,
        "w": 320,
        "h": 320
      },
      "rotated": false,
      "trimmed": false,
      "spriteSourceSize": {
        "x": 0,
        "y": 320,
        "w": 320,
        "h": 320
      },
      "sourceSize": {
        "w": 320,
        "h": 320
      }
    },
    "black-rook": {
      "frame": {
        "x": 1280,
        "y": 320,
        "w": 320,
        "h": 320
      },
      "rotated": false,
      "trimmed": false,
      "spriteSourceSize": {
        "x": 0,
        "y": 320,
        "w": 320,
        "h": 320
      },
      "sourceSize": {
        "w": 320,
        "h": 320
      }
    },
    "black-pawn": {
      "frame": {
        "x": 1600,
        "y": 320,
        "w": 320,
        "h": 320
      },
      "rotated": false,
      "trimmed": false,
      "spriteSourceSize": {
        "x": 0,
        "y": 0,
        "w": 320,
        "h": 320
      },
      "sourceSize": {
        "w": 320,
        "h": 320
      }
    }
  }
}
